syncs3.py
syncs3-0.1.1.dist-info/METADATA
syncs3-0.1.1.dist-info/WHEEL
syncs3-0.1.1.dist-info/top_level.txt
syncs3-0.1.1.dist-info/RECORD
