Metadata-Version: 2.1
Name: syncs3
Version: 0.1.1
Summary: A package to give a document sync experience(and eficciency) like "repo sync", or "awscli s3 sync", and so forth.
Home-page: https://github.com/TechnocultureResearch/syncs3
Author: Technoculture
Author-email: tanishaagrawal2015@gmail.com
License: MIT License
Platform: UNKNOWN
Classifier: Development Status :: 1 - Planning
Classifier: Intended Audience :: Science/Research
Classifier: License :: OSI Approved :: MIT License
Classifier: Operating System :: POSIX :: Linux
Classifier: Programming Language :: Python :: 3.5
Classifier: Programming Language :: Python :: 3.6
Classifier: Programming Language :: Python :: 3.7
Classifier: Programming Language :: Python :: 3.8
Requires-Dist: boto3 (>=1.24.87)
